{
  "version": "7",
  "dialect": "postgresql",
  "entries": [
    {
      "idx": 0,
      "version": "7",
      "when": 1770230042814,
      "tag": "0000_next_scorpion",
      "breakpoints": true
    },
    {
      "idx": 1,
      "version": "7",
      "when": 1770237055193,
      "tag": "0001_crazy_lucky_pierre",
      "breakpoints": true
    },
    {
      "idx": 2,
      "version": "7",
      "when": 1770647995037,
      "tag": "0002_milky_payback",
      "breakpoints": true
    },
    {
      "idx": 3,
      "version": "7",
      "when": 1771361161901,
      "tag": "0003_parallel_human_robot",
      "breakpoints": true
    }
  ]
}